ec2api_tempest_plugin/__init__.py
ec2api_tempest_plugin/base.py
ec2api_tempest_plugin/botocoreclient.py
ec2api_tempest_plugin/config.py
ec2api_tempest_plugin/config_opts.py
ec2api_tempest_plugin/plugin.py
ec2api_tempest_plugin/ssh.py
ec2api_tempest_plugin/api/__init__.py
ec2api_tempest_plugin/api/test_addresses.py
ec2api_tempest_plugin/api/test_customer_gateways.py
ec2api_tempest_plugin/api/test_dhcp_options.py
ec2api_tempest_plugin/api/test_images.py
ec2api_tempest_plugin/api/test_instance_attributes.py
ec2api_tempest_plugin/api/test_instances.py
ec2api_tempest_plugin/api/test_instances_ebs.py
ec2api_tempest_plugin/api/test_instances_vpc.py
ec2api_tempest_plugin/api/test_internet_gateways.py
ec2api_tempest_plugin/api/test_key_pairs.py
ec2api_tempest_plugin/api/test_network_interfaces.py
ec2api_tempest_plugin/api/test_regions.py
ec2api_tempest_plugin/api/test_routes.py
ec2api_tempest_plugin/api/test_security_groups.py
ec2api_tempest_plugin/api/test_snapshots.py
ec2api_tempest_plugin/api/test_subnets.py
ec2api_tempest_plugin/api/test_tags.py
ec2api_tempest_plugin/api/test_volumes.py
ec2api_tempest_plugin/api/test_vpcs.py
ec2api_tempest_plugin/api/test_vpn_connections.py
ec2api_tempest_plugin/api/test_vpn_gateways.py
ec2api_tempest_plugin/scenario/__init__.py
ec2api_tempest_plugin/scenario/base.py
ec2api_tempest_plugin/scenario/test_ebs_instances.py
ec2api_tempest_plugin/scenario/test_instance_restart.py
ec2api_tempest_plugin/scenario/test_instances.py
ec2api_tempest_plugin/scenario/test_instances_in_vpc.py
ec2api_tempest_plugin/scenario/test_paging.py
ec2api_tempest_plugin/scenario/test_vpc_addresses.py
ec2api_tempest_plugin/scenario/test_vpn.py
ec2api_tempest_plugin-1.7.0.dist-info/AUTHORS
ec2api_tempest_plugin-1.7.0.dist-info/LICENSE
ec2api_tempest_plugin-1.7.0.dist-info/METADATA
ec2api_tempest_plugin-1.7.0.dist-info/WHEEL
ec2api_tempest_plugin-1.7.0.dist-info/entry_points.txt
ec2api_tempest_plugin-1.7.0.dist-info/pbr.json
ec2api_tempest_plugin-1.7.0.dist-info/top_level.txt
ec2api_tempest_plugin-1.7.0.dist-info/RECORD
